privex/__init__.py
privex/pyrewall/PyreLexer.py
privex/pyrewall/PyreParser.py
privex/pyrewall/RuleBuilder.py
privex/pyrewall/RuleParser.py
privex/pyrewall/__init__.py
privex/pyrewall/conf.py
privex/pyrewall/core.py
privex/pyrewall/exceptions.py
privex/pyrewall/repl.py
privex/pyrewall/types.py
privex/pyrewall/configs/example/other.pyre
privex/pyrewall/configs/example/rules.v4
privex/pyrewall/configs/example/test.pyre
privex/pyrewall/configs/example/tpl_test.pyre
privex/pyrewall/configs/templates/icmp.pyre
privex/pyrewall/configs/templates/icmp6.pyre
privex/pyrewall/configs/templates/sane.pyre
privex/pyrewall/files/pyrewall.service
pyrewall-0.12.0.data/scripts/pyre
pyrewall-0.12.0.data/scripts/pyre-parse
pyrewall-0.12.0.data/scripts/pyre-parse4
pyrewall-0.12.0.data/scripts/pyre-parse6
pyrewall-0.12.0.dist-info/LICENSE
pyrewall-0.12.0.dist-info/METADATA
pyrewall-0.12.0.dist-info/WHEEL
pyrewall-0.12.0.dist-info/top_level.txt
pyrewall-0.12.0.dist-info/RECORD
