Metadata-Version: 2.1
Name: pyrewall
Version: 0.12.0
Summary: A Python tool / service for managing iptables firewalls with ease
Home-page: https://github.com/Privex/pyrewall
Author: Chris (Someguy123) @ Privex
Author-email: chris@privex.io
License: MIT
Platform: UNKNOWN
Classifier: Programming Language :: Python :: 3
Classifier: Programming Language :: Python :: 3.6
Classifier: Programming Language :: Python :: 3.7
Classifier: Programming Language :: Python :: 3.8
Classifier: License :: OSI Approved :: MIT License
Classifier: Operating System :: POSIX :: Linux
Requires-Dist: privex-helpers (>=2.10.0)
Requires-Dist: python-dotenv
Requires-Dist: prompt-toolkit (>=2.0.0)
Requires-Dist: pygments
Requires-Dist: colorama
